npmworkon.py
npmworkon-0.1.0.dist-info/METADATA
npmworkon-0.1.0.dist-info/WHEEL
npmworkon-0.1.0.dist-info/entry_points.txt
npmworkon-0.1.0.dist-info/top_level.txt
npmworkon-0.1.0.dist-info/RECORD
