Metadata-Version: 2.1
Name: npmworkon
Version: 0.1.0
Summary: Node.js virtual environment wrapper on top of nodeenv
Home-page: https://github.com/s0h3ck/npmworkon/
Author: s0h3ck
Author-email: s0h3ck@gmail.com
License: MIT
Keywords: node npm virtual environment wrapper
Platform: UNKNOWN
Classifier: Programming Language :: Python :: 3
Classifier: License :: OSI Approved :: MIT License
Classifier: Operating System :: OS Independent
Classifier: Intended Audience :: Developers
Classifier: Topic :: Software Development :: Libraries :: Python Modules
Requires-Dist: nodeenv
